{"ts": false, "types": {"WA00-A04": {"id": 0, "de": "W: A00-A04", "color": "#0000d3", "unit": "F\u00e4lle", "unit1": "Fall", "showSum": 1}, "WA05-A14": {"id": 1, "de": "W: A05-A14", "color": "#0000d3", "unit": "F\u00e4lle", "unit1": "Fall", "showSum": 1}, "WA15-A34": {"id": 2, "de": "W: A15-A34", "color": "#0000d3", "unit": "F\u00e4lle", "unit1": "Fall", "showSum": 1}, "WA35-A59": {"id": 3, "de": "W: A35-A59", "color": "#0000d3", "unit": "F\u00e4lle", "unit1": "Fall", "showSum": 1}, "WA60-A79": {"id": 4, "de": "W: A60-A79", "color": "#0000d3", "unit": "F\u00e4lle", "unit1": "Fall", "showSum": 1}, "WA80+": {"id": 5, "de": "W: A80+", "color": "#0000d3", "unit": "F\u00e4lle", "unit1": "Fall", "showSum": 1}, "MA00-A04": {"id": 6, "de": "M: A00-A04", "color": "#0000d3", "unit": "F\u00e4lle", "unit1": "Fall", "showSum": 1}, "MA05-A14": {"id": 7, "de": "M: A05-A14", "color": "#0000d3", "unit": "F\u00e4lle", "unit1": "Fall", "showSum": 1}, "MA15-A34": {"id": 8, "de": "M: A15-A34", "color": "#0000d3", "unit": "F\u00e4lle", "unit1": "Fall", "showSum": 1}, "MA35-A59": {"id": 9, "de": "M: A35-A59", "color": "#0000d3", "unit": "F\u00e4lle", "unit1": "Fall", "showSum": 1}, "MA60-A79": {"id": 10, "de": "M: A60-A79", "color": "#0000d3", "unit": "F\u00e4lle", "unit1": "Fall", "showSum": 1}, "MA80+": {"id": 11, "de": "M: A80+", "color": "#0000d3", "unit": "F\u00e4lle", "unit1": "Fall", "showSum": 1}}, "values": {"ABG": {"WA00-A04": 158, "WA05-A14": 692, "WA15-A34": 1442, "WA35-A59": 2938, "WA60-A79": 1264, "WA80+": 891, "MA00-A04": 183, "MA05-A14": 693, "MA15-A34": 1313, "MA35-A59": 2429, "MA60-A79": 1157, "MA80+": 418}, "EIC": {"WA00-A04": 191, "WA05-A14": 670, "WA15-A34": 1241, "WA35-A59": 2182, "WA60-A79": 1016, "WA80+": 617, "MA00-A04": 207, "MA05-A14": 656, "MA15-A34": 1163, "MA35-A59": 1919, "MA60-A79": 960, "MA80+": 343}, "EA": {"WA00-A04": 0, "WA05-A14": 0, "WA15-A34": 0, "WA35-A59": 0, "WA60-A79": 0, "WA80+": 0, "MA00-A04": 0, "MA05-A14": 0, "MA15-A34": 0, "MA35-A59": 0, "MA60-A79": 0, "MA80+": 0}, "EF": {"WA00-A04": 384, "WA05-A14": 1531, "WA15-A34": 3566, "WA35-A59": 4815, "WA60-A79": 1554, "WA80+": 988, "MA00-A04": 366, "MA05-A14": 1580, "MA15-A34": 3186, "MA35-A59": 4220, "MA60-A79": 1447, "MA80+": 514}, "G": {"WA00-A04": 157, "WA05-A14": 649, "WA15-A34": 1492, "WA35-A59": 2344, "WA60-A79": 1111, "WA80+": 660, "MA00-A04": 180, "MA05-A14": 747, "MA15-A34": 1393, "MA35-A59": 2111, "MA60-A79": 925, "MA80+": 335}, "GTH": {"WA00-A04": 202, "WA05-A14": 1183, "WA15-A34": 2537, "WA35-A59": 4544, "WA60-A79": 1600, "WA80+": 914, "MA00-A04": 195, "MA05-A14": 1095, "MA15-A34": 2282, "MA35-A59": 3919, "MA60-A79": 1519, "MA80+": 496}, "GRZ": {"WA00-A04": 130, "WA05-A14": 696, "WA15-A34": 1642, "WA35-A59": 3520, "WA60-A79": 1482, "WA80+": 878, "MA00-A04": 159, "MA05-A14": 735, "MA15-A34": 1486, "MA35-A59": 2903, "MA60-A79": 1416, "MA80+": 442}, "HBN": {"WA00-A04": 111, "WA05-A14": 615, "WA15-A34": 1354, "WA35-A59": 2754, "WA60-A79": 1181, "WA80+": 632, "MA00-A04": 115, "MA05-A14": 637, "MA15-A34": 1154, "MA35-A59": 2366, "MA60-A79": 1131, "MA80+": 308}, "IK": {"WA00-A04": 239, "WA05-A14": 1075, "WA15-A34": 1791, "WA35-A59": 3328, "WA60-A79": 1377, "WA80+": 804, "MA00-A04": 268, "MA05-A14": 1164, "MA15-A34": 1672, "MA35-A59": 2950, "MA60-A79": 1237, "MA80+": 422}, "J": {"WA00-A04": 238, "WA05-A14": 803, "WA15-A34": 1607, "WA35-A59": 1880, "WA60-A79": 543, "WA80+": 379, "MA00-A04": 264, "MA05-A14": 826, "MA15-A34": 1557, "MA35-A59": 1758, "MA60-A79": 536, "MA80+": 220}, "KYF": {"WA00-A04": 91, "WA05-A14": 525, "WA15-A34": 1017, "WA35-A59": 1981, "WA60-A79": 795, "WA80+": 492, "MA00-A04": 99, "MA05-A14": 577, "MA15-A34": 936, "MA35-A59": 1599, "MA60-A79": 740, "MA80+": 233}, "NDH": {"WA00-A04": 124, "WA05-A14": 497, "WA15-A34": 841, "WA35-A59": 1468, "WA60-A79": 554, "WA80+": 248, "MA00-A04": 128, "MA05-A14": 522, "MA15-A34": 745, "MA35-A59": 1342, "MA60-A79": 538, "MA80+": 142}, "SHK": {"WA00-A04": 179, "WA05-A14": 791, "WA15-A34": 1235, "WA35-A59": 2523, "WA60-A79": 1022, "WA80+": 451, "MA00-A04": 160, "MA05-A14": 789, "MA15-A34": 1108, "MA35-A59": 2239, "MA60-A79": 924, "MA80+": 262}, "SOK": {"WA00-A04": 114, "WA05-A14": 665, "WA15-A34": 1545, "WA35-A59": 3326, "WA60-A79": 1337, "WA80+": 591, "MA00-A04": 133, "MA05-A14": 711, "MA15-A34": 1478, "MA35-A59": 2781, "MA60-A79": 1275, "MA80+": 337}, "SLF": {"WA00-A04": 144, "WA05-A14": 828, "WA15-A34": 1723, "WA35-A59": 3672, "WA60-A79": 1483, "WA80+": 896, "MA00-A04": 161, "MA05-A14": 876, "MA15-A34": 1595, "MA35-A59": 3087, "MA60-A79": 1371, "MA80+": 426}, "SM": {"WA00-A04": 229, "WA05-A14": 1189, "WA15-A34": 2313, "WA35-A59": 4499, "WA60-A79": 1945, "WA80+": 968, "MA00-A04": 239, "MA05-A14": 1213, "MA15-A34": 2172, "MA35-A59": 3752, "MA60-A79": 1877, "MA80+": 565}, "SOM": {"WA00-A04": 129, "WA05-A14": 506, "WA15-A34": 1096, "WA35-A59": 2077, "WA60-A79": 889, "WA80+": 402, "MA00-A04": 108, "MA05-A14": 549, "MA15-A34": 963, "MA35-A59": 1918, "MA60-A79": 809, "MA80+": 208}, "SON": {"WA00-A04": 116, "WA05-A14": 517, "WA15-A34": 1078, "WA35-A59": 2124, "WA60-A79": 959, "WA80+": 495, "MA00-A04": 108, "MA05-A14": 558, "MA15-A34": 994, "MA35-A59": 1908, "MA60-A79": 875, "MA80+": 270}, "SHL": {"WA00-A04": 46, "WA05-A14": 259, "WA15-A34": 551, "WA35-A59": 922, "WA60-A79": 456, "WA80+": 260, "MA00-A04": 50, "MA05-A14": 268, "MA15-A34": 582, "MA35-A59": 840, "MA60-A79": 425, "MA80+": 129}, "UH": {"WA00-A04": 147, "WA05-A14": 772, "WA15-A34": 1559, "WA35-A59": 2951, "WA60-A79": 1225, "WA80+": 736, "MA00-A04": 146, "MA05-A14": 764, "MA15-A34": 1405, "MA35-A59": 2488, "MA60-A79": 1138, "MA80+": 402}, "WAK": {"WA00-A04": 243, "WA05-A14": 1115, "WA15-A34": 2352, "WA35-A59": 4386, "WA60-A79": 1700, "WA80+": 913, "MA00-A04": 251, "MA05-A14": 1204, "MA15-A34": 2149, "MA35-A59": 3925, "MA60-A79": 1649, "MA80+": 493}, "WE": {"WA00-A04": 149, "WA05-A14": 644, "WA15-A34": 909, "WA35-A59": 1330, "WA60-A79": 426, "WA80+": 303, "MA00-A04": 155, "MA05-A14": 592, "MA15-A34": 804, "MA35-A59": 1104, "MA60-A79": 374, "MA80+": 140}, "AP": {"WA00-A04": 178, "WA05-A14": 807, "WA15-A34": 1229, "WA35-A59": 2176, "WA60-A79": 766, "WA80+": 321, "MA00-A04": 182, "MA05-A14": 810, "MA15-A34": 1051, "MA35-A59": 1937, "MA60-A79": 717, "MA80+": 166}}}