{"ts": false, "types": {"WA00-A04": {"id": 0, "de": "W: A00-A04", "color": "#0000d3", "unit": "F\u00e4lle", "unit1": "Fall", "showSum": 1}, "WA05-A14": {"id": 1, "de": "W: A05-A14", "color": "#0000d3", "unit": "F\u00e4lle", "unit1": "Fall", "showSum": 1}, "WA15-A34": {"id": 2, "de": "W: A15-A34", "color": "#0000d3", "unit": "F\u00e4lle", "unit1": "Fall", "showSum": 1}, "WA35-A59": {"id": 3, "de": "W: A35-A59", "color": "#0000d3", "unit": "F\u00e4lle", "unit1": "Fall", "showSum": 1}, "WA60-A79": {"id": 4, "de": "W: A60-A79", "color": "#0000d3", "unit": "F\u00e4lle", "unit1": "Fall", "showSum": 1}, "WA80+": {"id": 5, "de": "W: A80+", "color": "#0000d3", "unit": "F\u00e4lle", "unit1": "Fall", "showSum": 1}, "MA00-A04": {"id": 6, "de": "M: A00-A04", "color": "#0000d3", "unit": "F\u00e4lle", "unit1": "Fall", "showSum": 1}, "MA05-A14": {"id": 7, "de": "M: A05-A14", "color": "#0000d3", "unit": "F\u00e4lle", "unit1": "Fall", "showSum": 1}, "MA15-A34": {"id": 8, "de": "M: A15-A34", "color": "#0000d3", "unit": "F\u00e4lle", "unit1": "Fall", "showSum": 1}, "MA35-A59": {"id": 9, "de": "M: A35-A59", "color": "#0000d3", "unit": "F\u00e4lle", "unit1": "Fall", "showSum": 1}, "MA60-A79": {"id": 10, "de": "M: A60-A79", "color": "#0000d3", "unit": "F\u00e4lle", "unit1": "Fall", "showSum": 1}, "MA80+": {"id": 11, "de": "M: A80+", "color": "#0000d3", "unit": "F\u00e4lle", "unit1": "Fall", "showSum": 1}}, "values": {"ABG": {"WA00-A04": 16, "WA05-A14": 68, "WA15-A34": 96, "WA35-A59": 179, "WA60-A79": 65, "WA80+": 14, "MA00-A04": 16, "MA05-A14": 55, "MA15-A34": 94, "MA35-A59": 201, "MA60-A79": 49, "MA80+": 6}, "EIC": {"WA00-A04": 14, "WA05-A14": 50, "WA15-A34": 75, "WA35-A59": 98, "WA60-A79": 20, "WA80+": 4, "MA00-A04": 14, "MA05-A14": 48, "MA15-A34": 65, "MA35-A59": 106, "MA60-A79": 21, "MA80+": 4}, "EA": {"WA00-A04": 0, "WA05-A14": 0, "WA15-A34": 0, "WA35-A59": 0, "WA60-A79": 0, "WA80+": 0, "MA00-A04": 0, "MA05-A14": 0, "MA15-A34": 0, "MA35-A59": 0, "MA60-A79": 0, "MA80+": 0}, "EF": {"WA00-A04": 15, "WA05-A14": 81, "WA15-A34": 146, "WA35-A59": 178, "WA60-A79": 38, "WA80+": 12, "MA00-A04": 25, "MA05-A14": 96, "MA15-A34": 141, "MA35-A59": 141, "MA60-A79": 28, "MA80+": 7}, "G": {"WA00-A04": 7, "WA05-A14": 22, "WA15-A34": 49, "WA35-A59": 68, "WA60-A79": 17, "WA80+": 12, "MA00-A04": 7, "MA05-A14": 22, "MA15-A34": 64, "MA35-A59": 59, "MA60-A79": 18, "MA80+": 2}, "GTH": {"WA00-A04": 9, "WA05-A14": 55, "WA15-A34": 116, "WA35-A59": 153, "WA60-A79": 47, "WA80+": 21, "MA00-A04": 5, "MA05-A14": 58, "MA15-A34": 114, "MA35-A59": 136, "MA60-A79": 54, "MA80+": 7}, "GRZ": {"WA00-A04": 26, "WA05-A14": 84, "WA15-A34": 165, "WA35-A59": 326, "WA60-A79": 108, "WA80+": 31, "MA00-A04": 14, "MA05-A14": 91, "MA15-A34": 207, "MA35-A59": 302, "MA60-A79": 105, "MA80+": 17}, "HBN": {"WA00-A04": 9, "WA05-A14": 39, "WA15-A34": 119, "WA35-A59": 213, "WA60-A79": 62, "WA80+": 32, "MA00-A04": 10, "MA05-A14": 49, "MA15-A34": 86, "MA35-A59": 183, "MA60-A79": 62, "MA80+": 10}, "IK": {"WA00-A04": 9, "WA05-A14": 40, "WA15-A34": 94, "WA35-A59": 120, "WA60-A79": 39, "WA80+": 15, "MA00-A04": 9, "MA05-A14": 31, "MA15-A34": 131, "MA35-A59": 113, "MA60-A79": 34, "MA80+": 11}, "J": {"WA00-A04": 39, "WA05-A14": 110, "WA15-A34": 285, "WA35-A59": 220, "WA60-A79": 41, "WA80+": 23, "MA00-A04": 41, "MA05-A14": 112, "MA15-A34": 260, "MA35-A59": 211, "MA60-A79": 29, "MA80+": 15}, "KYF": {"WA00-A04": 7, "WA05-A14": 21, "WA15-A34": 46, "WA35-A59": 68, "WA60-A79": 23, "WA80+": 11, "MA00-A04": 10, "MA05-A14": 33, "MA15-A34": 42, "MA35-A59": 70, "MA60-A79": 21, "MA80+": 6}, "NDH": {"WA00-A04": 4, "WA05-A14": 34, "WA15-A34": 47, "WA35-A59": 76, "WA60-A79": 18, "WA80+": 20, "MA00-A04": 6, "MA05-A14": 29, "MA15-A34": 38, "MA35-A59": 64, "MA60-A79": 20, "MA80+": 14}, "SHK": {"WA00-A04": 14, "WA05-A14": 54, "WA15-A34": 89, "WA35-A59": 175, "WA60-A79": 66, "WA80+": 15, "MA00-A04": 16, "MA05-A14": 61, "MA15-A34": 108, "MA35-A59": 187, "MA60-A79": 62, "MA80+": 8}, "SOK": {"WA00-A04": 12, "WA05-A14": 28, "WA15-A34": 79, "WA35-A59": 131, "WA60-A79": 49, "WA80+": 13, "MA00-A04": 10, "MA05-A14": 26, "MA15-A34": 84, "MA35-A59": 141, "MA60-A79": 35, "MA80+": 5}, "SLF": {"WA00-A04": 11, "WA05-A14": 20, "WA15-A34": 79, "WA35-A59": 101, "WA60-A79": 54, "WA80+": 22, "MA00-A04": 9, "MA05-A14": 28, "MA15-A34": 71, "MA35-A59": 109, "MA60-A79": 40, "MA80+": 10}, "SM": {"WA00-A04": 15, "WA05-A14": 26, "WA15-A34": 103, "WA35-A59": 111, "WA60-A79": 38, "WA80+": 21, "MA00-A04": 19, "MA05-A14": 34, "MA15-A34": 66, "MA35-A59": 108, "MA60-A79": 42, "MA80+": 13}, "SOM": {"WA00-A04": 12, "WA05-A14": 46, "WA15-A34": 94, "WA35-A59": 190, "WA60-A79": 63, "WA80+": 19, "MA00-A04": 13, "MA05-A14": 56, "MA15-A34": 80, "MA35-A59": 172, "MA60-A79": 44, "MA80+": 12}, "SON": {"WA00-A04": 1, "WA05-A14": 27, "WA15-A34": 49, "WA35-A59": 74, "WA60-A79": 39, "WA80+": 10, "MA00-A04": 4, "MA05-A14": 25, "MA15-A34": 44, "MA35-A59": 95, "MA60-A79": 25, "MA80+": 3}, "SHL": {"WA00-A04": 2, "WA05-A14": 24, "WA15-A34": 39, "WA35-A59": 73, "WA60-A79": 30, "WA80+": 10, "MA00-A04": 4, "MA05-A14": 13, "MA15-A34": 45, "MA35-A59": 61, "MA60-A79": 22, "MA80+": 2}, "UH": {"WA00-A04": 23, "WA05-A14": 44, "WA15-A34": 83, "WA35-A59": 132, "WA60-A79": 27, "WA80+": 19, "MA00-A04": 9, "MA05-A14": 49, "MA15-A34": 86, "MA35-A59": 107, "MA60-A79": 35, "MA80+": 11}, "WAK": {"WA00-A04": 9, "WA05-A14": 81, "WA15-A34": 172, "WA35-A59": 241, "WA60-A79": 82, "WA80+": 19, "MA00-A04": 9, "MA05-A14": 92, "MA15-A34": 175, "MA35-A59": 228, "MA60-A79": 81, "MA80+": 14}, "WE": {"WA00-A04": 20, "WA05-A14": 70, "WA15-A34": 148, "WA35-A59": 117, "WA60-A79": 22, "WA80+": 8, "MA00-A04": 22, "MA05-A14": 58, "MA15-A34": 116, "MA35-A59": 108, "MA60-A79": 16, "MA80+": 3}, "AP": {"WA00-A04": 16, "WA05-A14": 70, "WA15-A34": 83, "WA35-A59": 134, "WA60-A79": 34, "WA80+": 15, "MA00-A04": 19, "MA05-A14": 74, "MA15-A34": 102, "MA35-A59": 128, "MA60-A79": 33, "MA80+": 7}}}