{"ts": false, "types": {"WA00-A04": {"id": 0, "de": "W: A00-A04", "color": "#0000d3", "unit": "F\u00e4lle", "unit1": "Fall", "showSum": 1}, "WA05-A14": {"id": 1, "de": "W: A05-A14", "color": "#0000d3", "unit": "F\u00e4lle", "unit1": "Fall", "showSum": 1}, "WA15-A34": {"id": 2, "de": "W: A15-A34", "color": "#0000d3", "unit": "F\u00e4lle", "unit1": "Fall", "showSum": 1}, "WA35-A59": {"id": 3, "de": "W: A35-A59", "color": "#0000d3", "unit": "F\u00e4lle", "unit1": "Fall", "showSum": 1}, "WA60-A79": {"id": 4, "de": "W: A60-A79", "color": "#0000d3", "unit": "F\u00e4lle", "unit1": "Fall", "showSum": 1}, "WA80+": {"id": 5, "de": "W: A80+", "color": "#0000d3", "unit": "F\u00e4lle", "unit1": "Fall", "showSum": 1}, "MA00-A04": {"id": 6, "de": "M: A00-A04", "color": "#0000d3", "unit": "F\u00e4lle", "unit1": "Fall", "showSum": 1}, "MA05-A14": {"id": 7, "de": "M: A05-A14", "color": "#0000d3", "unit": "F\u00e4lle", "unit1": "Fall", "showSum": 1}, "MA15-A34": {"id": 8, "de": "M: A15-A34", "color": "#0000d3", "unit": "F\u00e4lle", "unit1": "Fall", "showSum": 1}, "MA35-A59": {"id": 9, "de": "M: A35-A59", "color": "#0000d3", "unit": "F\u00e4lle", "unit1": "Fall", "showSum": 1}, "MA60-A79": {"id": 10, "de": "M: A60-A79", "color": "#0000d3", "unit": "F\u00e4lle", "unit1": "Fall", "showSum": 1}, "MA80+": {"id": 11, "de": "M: A80+", "color": "#0000d3", "unit": "F\u00e4lle", "unit1": "Fall", "showSum": 1}}, "values": {"ABG": {"WA00-A04": 157, "WA05-A14": 660, "WA15-A34": 1415, "WA35-A59": 2873, "WA60-A79": 1207, "WA80+": 735, "MA00-A04": 180, "MA05-A14": 680, "MA15-A34": 1292, "MA35-A59": 2363, "MA60-A79": 1084, "MA80+": 301}, "EIC": {"WA00-A04": 200, "WA05-A14": 687, "WA15-A34": 1281, "WA35-A59": 2254, "WA60-A79": 1005, "WA80+": 502, "MA00-A04": 214, "MA05-A14": 671, "MA15-A34": 1209, "MA35-A59": 1970, "MA60-A79": 926, "MA80+": 259}, "EA": {"WA00-A04": 0, "WA05-A14": 0, "WA15-A34": 0, "WA35-A59": 0, "WA60-A79": 0, "WA80+": 0, "MA00-A04": 0, "MA05-A14": 0, "MA15-A34": 0, "MA35-A59": 0, "MA60-A79": 0, "MA80+": 0}, "EF": {"WA00-A04": 398, "WA05-A14": 1580, "WA15-A34": 3753, "WA35-A59": 4993, "WA60-A79": 1567, "WA80+": 867, "MA00-A04": 385, "MA05-A14": 1642, "MA15-A34": 3354, "MA35-A59": 4393, "MA60-A79": 1413, "MA80+": 385}, "G": {"WA00-A04": 159, "WA05-A14": 666, "WA15-A34": 1531, "WA35-A59": 2402, "WA60-A79": 1088, "WA80+": 564, "MA00-A04": 184, "MA05-A14": 761, "MA15-A34": 1434, "MA35-A59": 2149, "MA60-A79": 874, "MA80+": 238}, "GTH": {"WA00-A04": 203, "WA05-A14": 1188, "WA15-A34": 2573, "WA35-A59": 4578, "WA60-A79": 1585, "WA80+": 816, "MA00-A04": 196, "MA05-A14": 1108, "MA15-A34": 2303, "MA35-A59": 3942, "MA60-A79": 1455, "MA80+": 406}, "GRZ": {"WA00-A04": 126, "WA05-A14": 673, "WA15-A34": 1612, "WA35-A59": 3454, "WA60-A79": 1440, "WA80+": 769, "MA00-A04": 157, "MA05-A14": 702, "MA15-A34": 1439, "MA35-A59": 2823, "MA60-A79": 1333, "MA80+": 347}, "HBN": {"WA00-A04": 110, "WA05-A14": 599, "WA15-A34": 1319, "WA35-A59": 2682, "WA60-A79": 1112, "WA80+": 504, "MA00-A04": 112, "MA05-A14": 627, "MA15-A34": 1136, "MA35-A59": 2303, "MA60-A79": 1039, "MA80+": 200}, "IK": {"WA00-A04": 242, "WA05-A14": 1078, "WA15-A34": 1809, "WA35-A59": 3345, "WA60-A79": 1346, "WA80+": 673, "MA00-A04": 270, "MA05-A14": 1171, "MA15-A34": 1685, "MA35-A59": 2965, "MA60-A79": 1158, "MA80+": 305}, "J": {"WA00-A04": 240, "WA05-A14": 787, "WA15-A34": 1566, "WA35-A59": 1832, "WA60-A79": 542, "WA80+": 334, "MA00-A04": 262, "MA05-A14": 817, "MA15-A34": 1517, "MA35-A59": 1723, "MA60-A79": 509, "MA80+": 181}, "KYF": {"WA00-A04": 92, "WA05-A14": 542, "WA15-A34": 1038, "WA35-A59": 2028, "WA60-A79": 777, "WA80+": 419, "MA00-A04": 99, "MA05-A14": 592, "MA15-A34": 961, "MA35-A59": 1645, "MA60-A79": 709, "MA80+": 186}, "NDH": {"WA00-A04": 131, "WA05-A14": 524, "WA15-A34": 896, "WA35-A59": 1541, "WA60-A79": 560, "WA80+": 233, "MA00-A04": 132, "MA05-A14": 549, "MA15-A34": 790, "MA35-A59": 1432, "MA60-A79": 531, "MA80+": 119}, "SHK": {"WA00-A04": 176, "WA05-A14": 785, "WA15-A34": 1213, "WA35-A59": 2480, "WA60-A79": 989, "WA80+": 390, "MA00-A04": 157, "MA05-A14": 773, "MA15-A34": 1092, "MA35-A59": 2184, "MA60-A79": 877, "MA80+": 198}, "SOK": {"WA00-A04": 115, "WA05-A14": 660, "WA15-A34": 1535, "WA35-A59": 3302, "WA60-A79": 1298, "WA80+": 504, "MA00-A04": 129, "MA05-A14": 705, "MA15-A34": 1480, "MA35-A59": 2738, "MA60-A79": 1200, "MA80+": 252}, "SLF": {"WA00-A04": 152, "WA05-A14": 845, "WA15-A34": 1778, "WA35-A59": 3713, "WA60-A79": 1453, "WA80+": 736, "MA00-A04": 164, "MA05-A14": 895, "MA15-A34": 1645, "MA35-A59": 3115, "MA60-A79": 1306, "MA80+": 301}, "SM": {"WA00-A04": 237, "WA05-A14": 1227, "WA15-A34": 2365, "WA35-A59": 4592, "WA60-A79": 1915, "WA80+": 805, "MA00-A04": 250, "MA05-A14": 1248, "MA15-A34": 2228, "MA35-A59": 3845, "MA60-A79": 1788, "MA80+": 410}, "SOM": {"WA00-A04": 126, "WA05-A14": 501, "WA15-A34": 1076, "WA35-A59": 2036, "WA60-A79": 847, "WA80+": 325, "MA00-A04": 108, "MA05-A14": 536, "MA15-A34": 946, "MA35-A59": 1868, "MA60-A79": 755, "MA80+": 155}, "SON": {"WA00-A04": 114, "WA05-A14": 516, "WA15-A34": 1074, "WA35-A59": 2110, "WA60-A79": 925, "WA80+": 404, "MA00-A04": 108, "MA05-A14": 554, "MA15-A34": 993, "MA35-A59": 1887, "MA60-A79": 823, "MA80+": 192}, "SHL": {"WA00-A04": 46, "WA05-A14": 252, "WA15-A34": 537, "WA35-A59": 897, "WA60-A79": 433, "WA80+": 200, "MA00-A04": 48, "MA05-A14": 269, "MA15-A34": 577, "MA35-A59": 813, "MA60-A79": 394, "MA80+": 85}, "UH": {"WA00-A04": 149, "WA05-A14": 780, "WA15-A34": 1593, "WA35-A59": 3010, "WA60-A79": 1208, "WA80+": 614, "MA00-A04": 150, "MA05-A14": 793, "MA15-A34": 1450, "MA35-A59": 2541, "MA60-A79": 1082, "MA80+": 289}, "WAK": {"WA00-A04": 248, "WA05-A14": 1139, "WA15-A34": 2385, "WA35-A59": 4426, "WA60-A79": 1659, "WA80+": 771, "MA00-A04": 256, "MA05-A14": 1222, "MA15-A34": 2188, "MA35-A59": 3960, "MA60-A79": 1566, "MA80+": 377}, "WE": {"WA00-A04": 144, "WA05-A14": 636, "WA15-A34": 894, "WA35-A59": 1313, "WA60-A79": 416, "WA80+": 247, "MA00-A04": 153, "MA05-A14": 591, "MA15-A34": 784, "MA35-A59": 1090, "MA60-A79": 344, "MA80+": 103}, "AP": {"WA00-A04": 184, "WA05-A14": 837, "WA15-A34": 1266, "WA35-A59": 2240, "WA60-A79": 761, "WA80+": 290, "MA00-A04": 186, "MA05-A14": 823, "MA15-A34": 1072, "MA35-A59": 1993, "MA60-A79": 707, "MA80+": 134}}}