{"ts": false, "types": {"WA00-A04": {"id": 0, "de": "W: A00-A04", "color": "#0000d3", "unit": "F\u00e4lle", "unit1": "Fall", "showSum": 1}, "WA05-A14": {"id": 1, "de": "W: A05-A14", "color": "#0000d3", "unit": "F\u00e4lle", "unit1": "Fall", "showSum": 1}, "WA15-A34": {"id": 2, "de": "W: A15-A34", "color": "#0000d3", "unit": "F\u00e4lle", "unit1": "Fall", "showSum": 1}, "WA35-A59": {"id": 3, "de": "W: A35-A59", "color": "#0000d3", "unit": "F\u00e4lle", "unit1": "Fall", "showSum": 1}, "WA60-A79": {"id": 4, "de": "W: A60-A79", "color": "#0000d3", "unit": "F\u00e4lle", "unit1": "Fall", "showSum": 1}, "WA80+": {"id": 5, "de": "W: A80+", "color": "#0000d3", "unit": "F\u00e4lle", "unit1": "Fall", "showSum": 1}, "MA00-A04": {"id": 6, "de": "M: A00-A04", "color": "#0000d3", "unit": "F\u00e4lle", "unit1": "Fall", "showSum": 1}, "MA05-A14": {"id": 7, "de": "M: A05-A14", "color": "#0000d3", "unit": "F\u00e4lle", "unit1": "Fall", "showSum": 1}, "MA15-A34": {"id": 8, "de": "M: A15-A34", "color": "#0000d3", "unit": "F\u00e4lle", "unit1": "Fall", "showSum": 1}, "MA35-A59": {"id": 9, "de": "M: A35-A59", "color": "#0000d3", "unit": "F\u00e4lle", "unit1": "Fall", "showSum": 1}, "MA60-A79": {"id": 10, "de": "M: A60-A79", "color": "#0000d3", "unit": "F\u00e4lle", "unit1": "Fall", "showSum": 1}, "MA80+": {"id": 11, "de": "M: A80+", "color": "#0000d3", "unit": "F\u00e4lle", "unit1": "Fall", "showSum": 1}}, "values": {"ABG": {"WA00-A04": 177, "WA05-A14": 752, "WA15-A34": 1549, "WA35-A59": 3082, "WA60-A79": 1324, "WA80+": 901, "MA00-A04": 197, "MA05-A14": 758, "MA15-A34": 1406, "MA35-A59": 2612, "MA60-A79": 1202, "MA80+": 420}, "EIC": {"WA00-A04": 216, "WA05-A14": 762, "WA15-A34": 1377, "WA35-A59": 2394, "WA60-A79": 1060, "WA80+": 625, "MA00-A04": 233, "MA05-A14": 744, "MA15-A34": 1296, "MA35-A59": 2115, "MA60-A79": 1010, "MA80+": 354}, "EA": {"WA00-A04": 0, "WA05-A14": 0, "WA15-A34": 0, "WA35-A59": 0, "WA60-A79": 0, "WA80+": 0, "MA00-A04": 0, "MA05-A14": 0, "MA15-A34": 0, "MA35-A59": 0, "MA60-A79": 0, "MA80+": 0}, "EF": {"WA00-A04": 419, "WA05-A14": 1719, "WA15-A34": 3971, "WA35-A59": 5288, "WA60-A79": 1662, "WA80+": 1017, "MA00-A04": 422, "MA05-A14": 1801, "MA15-A34": 3558, "MA35-A59": 4627, "MA60-A79": 1530, "MA80+": 528}, "G": {"WA00-A04": 170, "WA05-A14": 701, "WA15-A34": 1602, "WA35-A59": 2491, "WA60-A79": 1147, "WA80+": 678, "MA00-A04": 196, "MA05-A14": 795, "MA15-A34": 1511, "MA35-A59": 2237, "MA60-A79": 970, "MA80+": 339}, "GTH": {"WA00-A04": 218, "WA05-A14": 1268, "WA15-A34": 2716, "WA35-A59": 4774, "WA60-A79": 1670, "WA80+": 939, "MA00-A04": 202, "MA05-A14": 1194, "MA15-A34": 2452, "MA35-A59": 4134, "MA60-A79": 1588, "MA80+": 508}, "GRZ": {"WA00-A04": 150, "WA05-A14": 757, "WA15-A34": 1772, "WA35-A59": 3779, "WA60-A79": 1565, "WA80+": 903, "MA00-A04": 170, "MA05-A14": 791, "MA15-A34": 1623, "MA35-A59": 3116, "MA60-A79": 1497, "MA80+": 454}, "HBN": {"WA00-A04": 118, "WA05-A14": 638, "WA15-A34": 1445, "WA35-A59": 2905, "WA60-A79": 1229, "WA80+": 654, "MA00-A04": 126, "MA05-A14": 679, "MA15-A34": 1234, "MA35-A59": 2514, "MA60-A79": 1181, "MA80+": 316}, "IK": {"WA00-A04": 255, "WA05-A14": 1145, "WA15-A34": 1937, "WA35-A59": 3512, "WA60-A79": 1433, "WA80+": 820, "MA00-A04": 279, "MA05-A14": 1226, "MA15-A34": 1852, "MA35-A59": 3124, "MA60-A79": 1288, "MA80+": 430}, "J": {"WA00-A04": 290, "WA05-A14": 932, "WA15-A34": 1917, "WA35-A59": 2115, "WA60-A79": 590, "WA80+": 408, "MA00-A04": 306, "MA05-A14": 963, "MA15-A34": 1832, "MA35-A59": 1977, "MA60-A79": 572, "MA80+": 240}, "KYF": {"WA00-A04": 103, "WA05-A14": 580, "WA15-A34": 1107, "WA35-A59": 2121, "WA60-A79": 839, "WA80+": 509, "MA00-A04": 113, "MA05-A14": 639, "MA15-A34": 1019, "MA35-A59": 1747, "MA60-A79": 784, "MA80+": 242}, "NDH": {"WA00-A04": 138, "WA05-A14": 574, "WA15-A34": 957, "WA35-A59": 1656, "WA60-A79": 596, "WA80+": 282, "MA00-A04": 140, "MA05-A14": 594, "MA15-A34": 856, "MA35-A59": 1518, "MA60-A79": 580, "MA80+": 160}, "SHK": {"WA00-A04": 190, "WA05-A14": 857, "WA15-A34": 1315, "WA35-A59": 2674, "WA60-A79": 1072, "WA80+": 462, "MA00-A04": 171, "MA05-A14": 865, "MA15-A34": 1213, "MA35-A59": 2399, "MA60-A79": 982, "MA80+": 272}, "SOK": {"WA00-A04": 134, "WA05-A14": 701, "WA15-A34": 1633, "WA35-A59": 3452, "WA60-A79": 1379, "WA80+": 603, "MA00-A04": 140, "MA05-A14": 748, "MA15-A34": 1570, "MA35-A59": 2912, "MA60-A79": 1303, "MA80+": 337}, "SLF": {"WA00-A04": 166, "WA05-A14": 876, "WA15-A34": 1873, "WA35-A59": 3859, "WA60-A79": 1565, "WA80+": 924, "MA00-A04": 175, "MA05-A14": 935, "MA15-A34": 1727, "MA35-A59": 3284, "MA60-A79": 1435, "MA80+": 440}, "SM": {"WA00-A04": 257, "WA05-A14": 1266, "WA15-A34": 2496, "WA35-A59": 4770, "WA60-A79": 2031, "WA80+": 998, "MA00-A04": 274, "MA05-A14": 1317, "MA15-A34": 2338, "MA35-A59": 4011, "MA60-A79": 1971, "MA80+": 584}, "SOM": {"WA00-A04": 145, "WA05-A14": 574, "WA15-A34": 1173, "WA35-A59": 2239, "WA60-A79": 935, "WA80+": 421, "MA00-A04": 127, "MA05-A14": 615, "MA15-A34": 1033, "MA35-A59": 2052, "MA60-A79": 850, "MA80+": 218}, "SON": {"WA00-A04": 116, "WA05-A14": 545, "WA15-A34": 1127, "WA35-A59": 2197, "WA60-A79": 995, "WA80+": 498, "MA00-A04": 113, "MA05-A14": 590, "MA15-A34": 1045, "MA35-A59": 2017, "MA60-A79": 895, "MA80+": 273}, "SHL": {"WA00-A04": 49, "WA05-A14": 279, "WA15-A34": 585, "WA35-A59": 985, "WA60-A79": 480, "WA80+": 270, "MA00-A04": 52, "MA05-A14": 288, "MA15-A34": 629, "MA35-A59": 889, "MA60-A79": 442, "MA80+": 130}, "UH": {"WA00-A04": 177, "WA05-A14": 848, "WA15-A34": 1707, "WA35-A59": 3198, "WA60-A79": 1288, "WA80+": 765, "MA00-A04": 165, "MA05-A14": 858, "MA15-A34": 1563, "MA35-A59": 2696, "MA60-A79": 1197, "MA80+": 422}, "WAK": {"WA00-A04": 272, "WA05-A14": 1268, "WA15-A34": 2641, "WA35-A59": 4792, "WA60-A79": 1801, "WA80+": 944, "MA00-A04": 272, "MA05-A14": 1364, "MA15-A34": 2426, "MA35-A59": 4287, "MA60-A79": 1769, "MA80+": 513}, "WE": {"WA00-A04": 168, "WA05-A14": 722, "WA15-A34": 1072, "WA35-A59": 1439, "WA60-A79": 454, "WA80+": 308, "MA00-A04": 175, "MA05-A14": 664, "MA15-A34": 920, "MA35-A59": 1220, "MA60-A79": 392, "MA80+": 142}, "AP": {"WA00-A04": 207, "WA05-A14": 933, "WA15-A34": 1376, "WA35-A59": 2405, "WA60-A79": 820, "WA80+": 342, "MA00-A04": 216, "MA05-A14": 946, "MA15-A34": 1195, "MA35-A59": 2160, "MA60-A79": 772, "MA80+": 178}}}