{"ts": false, "types": {"WA00-A04": {"id": 0, "de": "W: A00-A04", "color": "#0000d3", "unit": "F\u00e4lle", "unit1": "Fall", "showSum": 1}, "WA05-A14": {"id": 1, "de": "W: A05-A14", "color": "#0000d3", "unit": "F\u00e4lle", "unit1": "Fall", "showSum": 1}, "WA15-A34": {"id": 2, "de": "W: A15-A34", "color": "#0000d3", "unit": "F\u00e4lle", "unit1": "Fall", "showSum": 1}, "WA35-A59": {"id": 3, "de": "W: A35-A59", "color": "#0000d3", "unit": "F\u00e4lle", "unit1": "Fall", "showSum": 1}, "WA60-A79": {"id": 4, "de": "W: A60-A79", "color": "#0000d3", "unit": "F\u00e4lle", "unit1": "Fall", "showSum": 1}, "WA80+": {"id": 5, "de": "W: A80+", "color": "#0000d3", "unit": "F\u00e4lle", "unit1": "Fall", "showSum": 1}, "MA00-A04": {"id": 6, "de": "M: A00-A04", "color": "#0000d3", "unit": "F\u00e4lle", "unit1": "Fall", "showSum": 1}, "MA05-A14": {"id": 7, "de": "M: A05-A14", "color": "#0000d3", "unit": "F\u00e4lle", "unit1": "Fall", "showSum": 1}, "MA15-A34": {"id": 8, "de": "M: A15-A34", "color": "#0000d3", "unit": "F\u00e4lle", "unit1": "Fall", "showSum": 1}, "MA35-A59": {"id": 9, "de": "M: A35-A59", "color": "#0000d3", "unit": "F\u00e4lle", "unit1": "Fall", "showSum": 1}, "MA60-A79": {"id": 10, "de": "M: A60-A79", "color": "#0000d3", "unit": "F\u00e4lle", "unit1": "Fall", "showSum": 1}, "MA80+": {"id": 11, "de": "M: A80+", "color": "#0000d3", "unit": "F\u00e4lle", "unit1": "Fall", "showSum": 1}}, "values": {"ABG": {"WA00-A04": 7, "WA05-A14": 21, "WA15-A34": 56, "WA35-A59": 127, "WA60-A79": 66, "WA80+": 27, "MA00-A04": 5, "MA05-A14": 18, "MA15-A34": 38, "MA35-A59": 108, "MA60-A79": 52, "MA80+": 18}, "EIC": {"WA00-A04": 4, "WA05-A14": 19, "WA15-A34": 87, "WA35-A59": 218, "WA60-A79": 84, "WA80+": 14, "MA00-A04": 6, "MA05-A14": 28, "MA15-A34": 113, "MA35-A59": 178, "MA60-A79": 77, "MA80+": 13}, "EA": {"WA00-A04": 0, "WA05-A14": 0, "WA15-A34": 0, "WA35-A59": 0, "WA60-A79": 0, "WA80+": 0, "MA00-A04": 0, "MA05-A14": 0, "MA15-A34": 0, "MA35-A59": 0, "MA60-A79": 0, "MA80+": 0}, "EF": {"WA00-A04": 2, "WA05-A14": 10, "WA15-A34": 104, "WA35-A59": 137, "WA60-A79": 48, "WA80+": 25, "MA00-A04": 4, "MA05-A14": 8, "MA15-A34": 108, "MA35-A59": 119, "MA60-A79": 36, "MA80+": 12}, "G": {"WA00-A04": 2, "WA05-A14": 3, "WA15-A34": 38, "WA35-A59": 69, "WA60-A79": 44, "WA80+": 13, "MA00-A04": 3, "MA05-A14": 5, "MA15-A34": 37, "MA35-A59": 56, "MA60-A79": 32, "MA80+": 7}, "GTH": {"WA00-A04": 5, "WA05-A14": 18, "WA15-A34": 46, "WA35-A59": 103, "WA60-A79": 46, "WA80+": 16, "MA00-A04": 6, "MA05-A14": 15, "MA15-A34": 53, "MA35-A59": 97, "MA60-A79": 54, "MA80+": 10}, "GRZ": {"WA00-A04": 4, "WA05-A14": 5, "WA15-A34": 44, "WA35-A59": 89, "WA60-A79": 41, "WA80+": 7, "MA00-A04": 3, "MA05-A14": 7, "MA15-A34": 38, "MA35-A59": 67, "MA60-A79": 41, "MA80+": 8}, "HBN": {"WA00-A04": 1, "WA05-A14": 3, "WA15-A34": 31, "WA35-A59": 61, "WA60-A79": 30, "WA80+": 24, "MA00-A04": 2, "MA05-A14": 2, "MA15-A34": 30, "MA35-A59": 55, "MA60-A79": 27, "MA80+": 10}, "IK": {"WA00-A04": 1, "WA05-A14": 9, "WA15-A34": 58, "WA35-A59": 78, "WA60-A79": 42, "WA80+": 16, "MA00-A04": 4, "MA05-A14": 9, "MA15-A34": 78, "MA35-A59": 72, "MA60-A79": 27, "MA80+": 16}, "J": {"WA00-A04": 11, "WA05-A14": 32, "WA15-A34": 269, "WA35-A59": 223, "WA60-A79": 67, "WA80+": 26, "MA00-A04": 16, "MA05-A14": 47, "MA15-A34": 214, "MA35-A59": 201, "MA60-A79": 72, "MA80+": 13}, "KYF": {"WA00-A04": 2, "WA05-A14": 9, "WA15-A34": 45, "WA35-A59": 94, "WA60-A79": 34, "WA80+": 7, "MA00-A04": 0, "MA05-A14": 4, "MA15-A34": 41, "MA35-A59": 63, "MA60-A79": 37, "MA80+": 13}, "NDH": {"WA00-A04": 3, "WA05-A14": 9, "WA15-A34": 32, "WA35-A59": 65, "WA60-A79": 31, "WA80+": 5, "MA00-A04": 1, "MA05-A14": 4, "MA15-A34": 23, "MA35-A59": 53, "MA60-A79": 29, "MA80+": 10}, "SHK": {"WA00-A04": 3, "WA05-A14": 11, "WA15-A34": 61, "WA35-A59": 132, "WA60-A79": 51, "WA80+": 8, "MA00-A04": 4, "MA05-A14": 16, "MA15-A34": 50, "MA35-A59": 98, "MA60-A79": 49, "MA80+": 2}, "SOK": {"WA00-A04": 1, "WA05-A14": 7, "WA15-A34": 35, "WA35-A59": 58, "WA60-A79": 39, "WA80+": 6, "MA00-A04": 0, "MA05-A14": 5, "MA15-A34": 25, "MA35-A59": 44, "MA60-A79": 24, "MA80+": 5}, "SLF": {"WA00-A04": 0, "WA05-A14": 2, "WA15-A34": 25, "WA35-A59": 48, "WA60-A79": 12, "WA80+": 10, "MA00-A04": 0, "MA05-A14": 7, "MA15-A34": 20, "MA35-A59": 41, "MA60-A79": 27, "MA80+": 6}, "SM": {"WA00-A04": 1, "WA05-A14": 12, "WA15-A34": 63, "WA35-A59": 123, "WA60-A79": 65, "WA80+": 25, "MA00-A04": 1, "MA05-A14": 11, "MA15-A34": 54, "MA35-A59": 105, "MA60-A79": 57, "MA80+": 10}, "SOM": {"WA00-A04": 0, "WA05-A14": 4, "WA15-A34": 21, "WA35-A59": 57, "WA60-A79": 22, "WA80+": 1, "MA00-A04": 0, "MA05-A14": 2, "MA15-A34": 15, "MA35-A59": 31, "MA60-A79": 20, "MA80+": 2}, "SON": {"WA00-A04": 3, "WA05-A14": 7, "WA15-A34": 32, "WA35-A59": 58, "WA60-A79": 26, "WA80+": 10, "MA00-A04": 2, "MA05-A14": 7, "MA15-A34": 29, "MA35-A59": 54, "MA60-A79": 26, "MA80+": 10}, "SHL": {"WA00-A04": 0, "WA05-A14": 1, "WA15-A34": 15, "WA35-A59": 24, "WA60-A79": 19, "WA80+": 2, "MA00-A04": 0, "MA05-A14": 0, "MA15-A34": 12, "MA35-A59": 17, "MA60-A79": 18, "MA80+": 3}, "UH": {"WA00-A04": 1, "WA05-A14": 3, "WA15-A34": 54, "WA35-A59": 105, "WA60-A79": 43, "WA80+": 11, "MA00-A04": 3, "MA05-A14": 6, "MA15-A34": 44, "MA35-A59": 90, "MA60-A79": 48, "MA80+": 10}, "WAK": {"WA00-A04": 4, "WA05-A14": 9, "WA15-A34": 93, "WA35-A59": 152, "WA60-A79": 68, "WA80+": 13, "MA00-A04": 7, "MA05-A14": 10, "MA15-A34": 85, "MA35-A59": 126, "MA60-A79": 51, "MA80+": 14}, "WE": {"WA00-A04": 15, "WA05-A14": 20, "WA15-A34": 100, "WA35-A59": 142, "WA60-A79": 40, "WA80+": 9, "MA00-A04": 8, "MA05-A14": 12, "MA15-A34": 89, "MA35-A59": 109, "MA60-A79": 43, "MA80+": 8}, "AP": {"WA00-A04": 2, "WA05-A14": 10, "WA15-A34": 69, "WA35-A59": 127, "WA60-A79": 39, "WA80+": 7, "MA00-A04": 0, "MA05-A14": 21, "MA15-A34": 52, "MA35-A59": 87, "MA60-A79": 28, "MA80+": 10}}}