{"ts": false, "types": {"WA00-A04": {"id": 0, "de": "W: A00-A04", "color": "#0000d3", "unit": "F\u00e4lle", "unit1": "Fall", "showSum": 1}, "WA05-A14": {"id": 1, "de": "W: A05-A14", "color": "#0000d3", "unit": "F\u00e4lle", "unit1": "Fall", "showSum": 1}, "WA15-A34": {"id": 2, "de": "W: A15-A34", "color": "#0000d3", "unit": "F\u00e4lle", "unit1": "Fall", "showSum": 1}, "WA35-A59": {"id": 3, "de": "W: A35-A59", "color": "#0000d3", "unit": "F\u00e4lle", "unit1": "Fall", "showSum": 1}, "WA60-A79": {"id": 4, "de": "W: A60-A79", "color": "#0000d3", "unit": "F\u00e4lle", "unit1": "Fall", "showSum": 1}, "WA80+": {"id": 5, "de": "W: A80+", "color": "#0000d3", "unit": "F\u00e4lle", "unit1": "Fall", "showSum": 1}, "MA00-A04": {"id": 6, "de": "M: A00-A04", "color": "#0000d3", "unit": "F\u00e4lle", "unit1": "Fall", "showSum": 1}, "MA05-A14": {"id": 7, "de": "M: A05-A14", "color": "#0000d3", "unit": "F\u00e4lle", "unit1": "Fall", "showSum": 1}, "MA15-A34": {"id": 8, "de": "M: A15-A34", "color": "#0000d3", "unit": "F\u00e4lle", "unit1": "Fall", "showSum": 1}, "MA35-A59": {"id": 9, "de": "M: A35-A59", "color": "#0000d3", "unit": "F\u00e4lle", "unit1": "Fall", "showSum": 1}, "MA60-A79": {"id": 10, "de": "M: A60-A79", "color": "#0000d3", "unit": "F\u00e4lle", "unit1": "Fall", "showSum": 1}, "MA80+": {"id": 11, "de": "M: A80+", "color": "#0000d3", "unit": "F\u00e4lle", "unit1": "Fall", "showSum": 1}}, "values": {"ABG": {"WA00-A04": 95, "WA05-A14": 358, "WA15-A34": 673, "WA35-A59": 1077, "WA60-A79": 312, "WA80+": 94, "MA00-A04": 107, "MA05-A14": 317, "MA15-A34": 587, "MA35-A59": 931, "MA60-A79": 251, "MA80+": 63}, "EIC": {"WA00-A04": 181, "WA05-A14": 589, "WA15-A34": 885, "WA35-A59": 1316, "WA60-A79": 329, "WA80+": 70, "MA00-A04": 193, "MA05-A14": 631, "MA15-A34": 693, "MA35-A59": 1113, "MA60-A79": 293, "MA80+": 54}, "EA": {"WA00-A04": 0, "WA05-A14": 0, "WA15-A34": 0, "WA35-A59": 0, "WA60-A79": 0, "WA80+": 0, "MA00-A04": 0, "MA05-A14": 0, "MA15-A34": 0, "MA35-A59": 0, "MA60-A79": 0, "MA80+": 0}, "EF": {"WA00-A04": 16, "WA05-A14": 57, "WA15-A34": 86, "WA35-A59": 96, "WA60-A79": 33, "WA80+": 62, "MA00-A04": 12, "MA05-A14": 67, "MA15-A34": 86, "MA35-A59": 89, "MA60-A79": 45, "MA80+": 32}, "G": {"WA00-A04": 32, "WA05-A14": 149, "WA15-A34": 372, "WA35-A59": 498, "WA60-A79": 152, "WA80+": 70, "MA00-A04": 35, "MA05-A14": 193, "MA15-A34": 351, "MA35-A59": 455, "MA60-A79": 149, "MA80+": 36}, "GTH": {"WA00-A04": 65, "WA05-A14": 205, "WA15-A34": 427, "WA35-A59": 636, "WA60-A79": 155, "WA80+": 40, "MA00-A04": 65, "MA05-A14": 209, "MA15-A34": 349, "MA35-A59": 497, "MA60-A79": 140, "MA80+": 19}, "GRZ": {"WA00-A04": 30, "WA05-A14": 168, "WA15-A34": 364, "WA35-A59": 586, "WA60-A79": 125, "WA80+": 57, "MA00-A04": 25, "MA05-A14": 177, "MA15-A34": 301, "MA35-A59": 473, "MA60-A79": 114, "MA80+": 27}, "HBN": {"WA00-A04": 37, "WA05-A14": 169, "WA15-A34": 364, "WA35-A59": 576, "WA60-A79": 167, "WA80+": 47, "MA00-A04": 38, "MA05-A14": 176, "MA15-A34": 324, "MA35-A59": 551, "MA60-A79": 150, "MA80+": 21}, "IK": {"WA00-A04": 56, "WA05-A14": 174, "WA15-A34": 279, "WA35-A59": 429, "WA60-A79": 134, "WA80+": 45, "MA00-A04": 49, "MA05-A14": 164, "MA15-A34": 247, "MA35-A59": 397, "MA60-A79": 133, "MA80+": 29}, "J": {"WA00-A04": 188, "WA05-A14": 486, "WA15-A34": 1045, "WA35-A59": 1001, "WA60-A79": 180, "WA80+": 62, "MA00-A04": 191, "MA05-A14": 486, "MA15-A34": 907, "MA35-A59": 890, "MA60-A79": 154, "MA80+": 41}, "KYF": {"WA00-A04": 20, "WA05-A14": 112, "WA15-A34": 211, "WA35-A59": 359, "WA60-A79": 114, "WA80+": 32, "MA00-A04": 26, "MA05-A14": 132, "MA15-A34": 172, "MA35-A59": 285, "MA60-A79": 99, "MA80+": 13}, "NDH": {"WA00-A04": 106, "WA05-A14": 336, "WA15-A34": 589, "WA35-A59": 822, "WA60-A79": 210, "WA80+": 115, "MA00-A04": 93, "MA05-A14": 378, "MA15-A34": 460, "MA35-A59": 723, "MA60-A79": 243, "MA80+": 55}, "SHK": {"WA00-A04": 130, "WA05-A14": 448, "WA15-A34": 712, "WA35-A59": 1174, "WA60-A79": 302, "WA80+": 113, "MA00-A04": 136, "MA05-A14": 472, "MA15-A34": 662, "MA35-A59": 1026, "MA60-A79": 254, "MA80+": 55}, "SOK": {"WA00-A04": 62, "WA05-A14": 253, "WA15-A34": 567, "WA35-A59": 817, "WA60-A79": 250, "WA80+": 52, "MA00-A04": 74, "MA05-A14": 255, "MA15-A34": 501, "MA35-A59": 732, "MA60-A79": 225, "MA80+": 30}, "SLF": {"WA00-A04": 54, "WA05-A14": 304, "WA15-A34": 508, "WA35-A59": 859, "WA60-A79": 237, "WA80+": 99, "MA00-A04": 61, "MA05-A14": 331, "MA15-A34": 487, "MA35-A59": 772, "MA60-A79": 235, "MA80+": 40}, "SM": {"WA00-A04": 81, "WA05-A14": 237, "WA15-A34": 439, "WA35-A59": 673, "WA60-A79": 199, "WA80+": 60, "MA00-A04": 76, "MA05-A14": 260, "MA15-A34": 391, "MA35-A59": 551, "MA60-A79": 173, "MA80+": 45}, "SOM": {"WA00-A04": 28, "WA05-A14": 159, "WA15-A34": 278, "WA35-A59": 414, "WA60-A79": 122, "WA80+": 35, "MA00-A04": 30, "MA05-A14": 178, "MA15-A34": 193, "MA35-A59": 349, "MA60-A79": 91, "MA80+": 28}, "SON": {"WA00-A04": 25, "WA05-A14": 140, "WA15-A34": 326, "WA35-A59": 483, "WA60-A79": 112, "WA80+": 54, "MA00-A04": 30, "MA05-A14": 148, "MA15-A34": 295, "MA35-A59": 463, "MA60-A79": 105, "MA80+": 31}, "SHL": {"WA00-A04": 8, "WA05-A14": 40, "WA15-A34": 98, "WA35-A59": 161, "WA60-A79": 59, "WA80+": 18, "MA00-A04": 9, "MA05-A14": 62, "MA15-A34": 94, "MA35-A59": 127, "MA60-A79": 57, "MA80+": 10}, "UH": {"WA00-A04": 64, "WA05-A14": 239, "WA15-A34": 412, "WA35-A59": 656, "WA60-A79": 177, "WA80+": 70, "MA00-A04": 50, "MA05-A14": 235, "MA15-A34": 329, "MA35-A59": 519, "MA60-A79": 144, "MA80+": 31}, "WAK": {"WA00-A04": 79, "WA05-A14": 393, "WA15-A34": 686, "WA35-A59": 1015, "WA60-A79": 250, "WA80+": 85, "MA00-A04": 80, "MA05-A14": 435, "MA15-A34": 611, "MA35-A59": 879, "MA60-A79": 270, "MA80+": 57}, "WE": {"WA00-A04": 65, "WA05-A14": 281, "WA15-A34": 589, "WA35-A59": 607, "WA60-A79": 156, "WA80+": 39, "MA00-A04": 56, "MA05-A14": 232, "MA15-A34": 507, "MA35-A59": 510, "MA60-A79": 136, "MA80+": 37}, "AP": {"WA00-A04": 66, "WA05-A14": 302, "WA15-A34": 463, "WA35-A59": 767, "WA60-A79": 182, "WA80+": 84, "MA00-A04": 70, "MA05-A14": 271, "MA15-A34": 409, "MA35-A59": 656, "MA60-A79": 176, "MA80+": 42}}}