{"ts": false, "types": {"WA00-A04": {"id": 0, "de": "W: A00-A04", "color": "#0000d3", "unit": "F\u00e4lle", "unit1": "Fall", "showSum": 1}, "WA05-A14": {"id": 1, "de": "W: A05-A14", "color": "#0000d3", "unit": "F\u00e4lle", "unit1": "Fall", "showSum": 1}, "WA15-A34": {"id": 2, "de": "W: A15-A34", "color": "#0000d3", "unit": "F\u00e4lle", "unit1": "Fall", "showSum": 1}, "WA35-A59": {"id": 3, "de": "W: A35-A59", "color": "#0000d3", "unit": "F\u00e4lle", "unit1": "Fall", "showSum": 1}, "WA60-A79": {"id": 4, "de": "W: A60-A79", "color": "#0000d3", "unit": "F\u00e4lle", "unit1": "Fall", "showSum": 1}, "WA80+": {"id": 5, "de": "W: A80+", "color": "#0000d3", "unit": "F\u00e4lle", "unit1": "Fall", "showSum": 1}, "MA00-A04": {"id": 6, "de": "M: A00-A04", "color": "#0000d3", "unit": "F\u00e4lle", "unit1": "Fall", "showSum": 1}, "MA05-A14": {"id": 7, "de": "M: A05-A14", "color": "#0000d3", "unit": "F\u00e4lle", "unit1": "Fall", "showSum": 1}, "MA15-A34": {"id": 8, "de": "M: A15-A34", "color": "#0000d3", "unit": "F\u00e4lle", "unit1": "Fall", "showSum": 1}, "MA35-A59": {"id": 9, "de": "M: A35-A59", "color": "#0000d3", "unit": "F\u00e4lle", "unit1": "Fall", "showSum": 1}, "MA60-A79": {"id": 10, "de": "M: A60-A79", "color": "#0000d3", "unit": "F\u00e4lle", "unit1": "Fall", "showSum": 1}, "MA80+": {"id": 11, "de": "M: A80+", "color": "#0000d3", "unit": "F\u00e4lle", "unit1": "Fall", "showSum": 1}}, "values": {"ABG": {"WA00-A04": 152, "WA05-A14": 638, "WA15-A34": 1360, "WA35-A59": 2807, "WA60-A79": 1174, "WA80+": 727, "MA00-A04": 174, "MA05-A14": 655, "MA15-A34": 1250, "MA35-A59": 2291, "MA60-A79": 1057, "MA80+": 294}, "EIC": {"WA00-A04": 192, "WA05-A14": 673, "WA15-A34": 1245, "WA35-A59": 2199, "WA60-A79": 989, "WA80+": 498, "MA00-A04": 207, "MA05-A14": 657, "MA15-A34": 1169, "MA35-A59": 1911, "MA60-A79": 899, "MA80+": 253}, "EA": {"WA00-A04": 0, "WA05-A14": 0, "WA15-A34": 0, "WA35-A59": 0, "WA60-A79": 0, "WA80+": 0, "MA00-A04": 0, "MA05-A14": 0, "MA15-A34": 0, "MA35-A59": 0, "MA60-A79": 0, "MA80+": 0}, "EF": {"WA00-A04": 391, "WA05-A14": 1554, "WA15-A34": 3656, "WA35-A59": 4902, "WA60-A79": 1543, "WA80+": 860, "MA00-A04": 381, "MA05-A14": 1603, "MA15-A34": 3263, "MA35-A59": 4291, "MA60-A79": 1388, "MA80+": 382}, "G": {"WA00-A04": 157, "WA05-A14": 651, "WA15-A34": 1497, "WA35-A59": 2338, "WA60-A79": 1072, "WA80+": 555, "MA00-A04": 179, "MA05-A14": 752, "MA15-A34": 1399, "MA35-A59": 2092, "MA60-A79": 852, "MA80+": 237}, "GTH": {"WA00-A04": 199, "WA05-A14": 1159, "WA15-A34": 2507, "WA35-A59": 4488, "WA60-A79": 1551, "WA80+": 806, "MA00-A04": 192, "MA05-A14": 1077, "MA15-A34": 2251, "MA35-A59": 3864, "MA60-A79": 1423, "MA80+": 405}, "GRZ": {"WA00-A04": 116, "WA05-A14": 626, "WA15-A34": 1512, "WA35-A59": 3266, "WA60-A79": 1373, "WA80+": 747, "MA00-A04": 146, "MA05-A14": 654, "MA15-A34": 1336, "MA35-A59": 2635, "MA60-A79": 1276, "MA80+": 335}, "HBN": {"WA00-A04": 104, "WA05-A14": 576, "WA15-A34": 1279, "WA35-A59": 2601, "WA60-A79": 1087, "WA80+": 487, "MA00-A04": 110, "MA05-A14": 594, "MA15-A34": 1080, "MA35-A59": 2220, "MA60-A79": 1014, "MA80+": 196}, "IK": {"WA00-A04": 240, "WA05-A14": 1076, "WA15-A34": 1804, "WA35-A59": 3341, "WA60-A79": 1339, "WA80+": 666, "MA00-A04": 269, "MA05-A14": 1170, "MA15-A34": 1680, "MA35-A59": 2957, "MA60-A79": 1147, "MA80+": 304}, "J": {"WA00-A04": 226, "WA05-A14": 734, "WA15-A34": 1498, "WA35-A59": 1746, "WA60-A79": 512, "WA80+": 326, "MA00-A04": 245, "MA05-A14": 772, "MA15-A34": 1462, "MA35-A59": 1623, "MA60-A79": 490, "MA80+": 170}, "KYF": {"WA00-A04": 91, "WA05-A14": 528, "WA15-A34": 1013, "WA35-A59": 1991, "WA60-A79": 764, "WA80+": 415, "MA00-A04": 97, "MA05-A14": 577, "MA15-A34": 934, "MA35-A59": 1592, "MA60-A79": 695, "MA80+": 184}, "NDH": {"WA00-A04": 126, "WA05-A14": 507, "WA15-A34": 854, "WA35-A59": 1498, "WA60-A79": 548, "WA80+": 226, "MA00-A04": 129, "MA05-A14": 533, "MA15-A34": 755, "MA35-A59": 1359, "MA60-A79": 519, "MA80+": 116}, "SHK": {"WA00-A04": 164, "WA05-A14": 741, "WA15-A34": 1160, "WA35-A59": 2386, "WA60-A79": 941, "WA80+": 373, "MA00-A04": 146, "MA05-A14": 728, "MA15-A34": 1056, "MA35-A59": 2083, "MA60-A79": 846, "MA80+": 191}, "SOK": {"WA00-A04": 113, "WA05-A14": 641, "WA15-A34": 1483, "WA35-A59": 3208, "WA60-A79": 1268, "WA80+": 494, "MA00-A04": 128, "MA05-A14": 680, "MA15-A34": 1437, "MA35-A59": 2655, "MA60-A79": 1167, "MA80+": 249}, "SLF": {"WA00-A04": 145, "WA05-A14": 831, "WA15-A34": 1735, "WA35-A59": 3668, "WA60-A79": 1429, "WA80+": 720, "MA00-A04": 160, "MA05-A14": 882, "MA15-A34": 1617, "MA35-A59": 3075, "MA60-A79": 1285, "MA80+": 292}, "SM": {"WA00-A04": 229, "WA05-A14": 1193, "WA15-A34": 2308, "WA35-A59": 4490, "WA60-A79": 1881, "WA80+": 793, "MA00-A04": 240, "MA05-A14": 1214, "MA15-A34": 2174, "MA35-A59": 3732, "MA60-A79": 1751, "MA80+": 404}, "SOM": {"WA00-A04": 121, "WA05-A14": 462, "WA15-A34": 1026, "WA35-A59": 1945, "WA60-A79": 814, "WA80+": 325, "MA00-A04": 102, "MA05-A14": 498, "MA15-A34": 905, "MA35-A59": 1769, "MA60-A79": 726, "MA80+": 151}, "SON": {"WA00-A04": 105, "WA05-A14": 495, "WA15-A34": 1028, "WA35-A59": 2034, "WA60-A79": 896, "WA80+": 400, "MA00-A04": 103, "MA05-A14": 535, "MA15-A34": 960, "MA35-A59": 1832, "MA60-A79": 798, "MA80+": 191}, "SHL": {"WA00-A04": 43, "WA05-A14": 235, "WA15-A34": 518, "WA35-A59": 856, "WA60-A79": 422, "WA80+": 195, "MA00-A04": 46, "MA05-A14": 248, "MA15-A34": 552, "MA35-A59": 772, "MA60-A79": 376, "MA80+": 83}, "UH": {"WA00-A04": 140, "WA05-A14": 751, "WA15-A34": 1535, "WA35-A59": 2907, "WA60-A79": 1174, "WA80+": 607, "MA00-A04": 145, "MA05-A14": 749, "MA15-A34": 1379, "MA35-A59": 2437, "MA60-A79": 1058, "MA80+": 283}, "WAK": {"WA00-A04": 241, "WA05-A14": 1100, "WA15-A34": 2302, "WA35-A59": 4296, "WA60-A79": 1629, "WA80+": 767, "MA00-A04": 246, "MA05-A14": 1177, "MA15-A34": 2112, "MA35-A59": 3837, "MA60-A79": 1526, "MA80+": 370}, "WE": {"WA00-A04": 139, "WA05-A14": 587, "WA15-A34": 851, "WA35-A59": 1245, "WA60-A79": 398, "WA80+": 240, "MA00-A04": 138, "MA05-A14": 541, "MA15-A34": 753, "MA35-A59": 1038, "MA60-A79": 333, "MA80+": 101}, "AP": {"WA00-A04": 180, "WA05-A14": 806, "WA15-A34": 1223, "WA35-A59": 2143, "WA60-A79": 734, "WA80+": 279, "MA00-A04": 179, "MA05-A14": 789, "MA15-A34": 1034, "MA35-A59": 1909, "MA60-A79": 679, "MA80+": 131}}}