{"ts": false, "types": {"WA00-A04": {"id": 0, "de": "W: A00-A04", "color": "#0000d3", "unit": "F\u00e4lle", "unit1": "Fall", "showSum": 1}, "WA05-A14": {"id": 1, "de": "W: A05-A14", "color": "#0000d3", "unit": "F\u00e4lle", "unit1": "Fall", "showSum": 1}, "WA15-A34": {"id": 2, "de": "W: A15-A34", "color": "#0000d3", "unit": "F\u00e4lle", "unit1": "Fall", "showSum": 1}, "WA35-A59": {"id": 3, "de": "W: A35-A59", "color": "#0000d3", "unit": "F\u00e4lle", "unit1": "Fall", "showSum": 1}, "WA60-A79": {"id": 4, "de": "W: A60-A79", "color": "#0000d3", "unit": "F\u00e4lle", "unit1": "Fall", "showSum": 1}, "WA80+": {"id": 5, "de": "W: A80+", "color": "#0000d3", "unit": "F\u00e4lle", "unit1": "Fall", "showSum": 1}, "MA00-A04": {"id": 6, "de": "M: A00-A04", "color": "#0000d3", "unit": "F\u00e4lle", "unit1": "Fall", "showSum": 1}, "MA05-A14": {"id": 7, "de": "M: A05-A14", "color": "#0000d3", "unit": "F\u00e4lle", "unit1": "Fall", "showSum": 1}, "MA15-A34": {"id": 8, "de": "M: A15-A34", "color": "#0000d3", "unit": "F\u00e4lle", "unit1": "Fall", "showSum": 1}, "MA35-A59": {"id": 9, "de": "M: A35-A59", "color": "#0000d3", "unit": "F\u00e4lle", "unit1": "Fall", "showSum": 1}, "MA60-A79": {"id": 10, "de": "M: A60-A79", "color": "#0000d3", "unit": "F\u00e4lle", "unit1": "Fall", "showSum": 1}, "MA80+": {"id": 11, "de": "M: A80+", "color": "#0000d3", "unit": "F\u00e4lle", "unit1": "Fall", "showSum": 1}}, "values": {"ABG": {"WA00-A04": 443, "WA05-A14": 1827, "WA15-A34": 3671, "WA35-A59": 6814, "WA60-A79": 2635, "WA80+": 1372, "MA00-A04": 490, "MA05-A14": 1835, "MA15-A34": 3326, "MA35-A59": 5673, "MA60-A79": 2284, "MA80+": 718}, "EIC": {"WA00-A04": 710, "WA05-A14": 2666, "WA15-A34": 4534, "WA35-A59": 7618, "WA60-A79": 2547, "WA80+": 1062, "MA00-A04": 803, "MA05-A14": 2666, "MA15-A34": 4078, "MA35-A59": 6445, "MA60-A79": 2409, "MA80+": 626}, "EA": {"WA00-A04": 0, "WA05-A14": 0, "WA15-A34": 0, "WA35-A59": 0, "WA60-A79": 0, "WA80+": 0, "MA00-A04": 0, "MA05-A14": 0, "MA15-A34": 0, "MA35-A59": 0, "MA60-A79": 0, "MA80+": 0}, "EF": {"WA00-A04": 1119, "WA05-A14": 4258, "WA15-A34": 10555, "WA35-A59": 13032, "WA60-A79": 3588, "WA80+": 1770, "MA00-A04": 1105, "MA05-A14": 4412, "MA15-A34": 9128, "MA35-A59": 11146, "MA60-A79": 3206, "MA80+": 977}, "G": {"WA00-A04": 398, "WA05-A14": 1713, "WA15-A34": 3943, "WA35-A59": 5798, "WA60-A79": 2264, "WA80+": 1102, "MA00-A04": 455, "MA05-A14": 1930, "MA15-A34": 3656, "MA35-A59": 5105, "MA60-A79": 1954, "MA80+": 590}, "GTH": {"WA00-A04": 511, "WA05-A14": 2752, "WA15-A34": 5791, "WA35-A59": 9558, "WA60-A79": 3036, "WA80+": 1323, "MA00-A04": 537, "MA05-A14": 2730, "MA15-A34": 5232, "MA35-A59": 8153, "MA60-A79": 2733, "MA80+": 741}, "GRZ": {"WA00-A04": 337, "WA05-A14": 1704, "WA15-A34": 3799, "WA35-A59": 7598, "WA60-A79": 2787, "WA80+": 1335, "MA00-A04": 348, "MA05-A14": 1830, "MA15-A34": 3496, "MA35-A59": 6299, "MA60-A79": 2565, "MA80+": 672}, "HBN": {"WA00-A04": 248, "WA05-A14": 1252, "WA15-A34": 2760, "WA35-A59": 5371, "WA60-A79": 1995, "WA80+": 859, "MA00-A04": 255, "MA05-A14": 1322, "MA15-A34": 2485, "MA35-A59": 4703, "MA60-A79": 1819, "MA80+": 436}, "IK": {"WA00-A04": 662, "WA05-A14": 2699, "WA15-A34": 4709, "WA35-A59": 7805, "WA60-A79": 2826, "WA80+": 1310, "MA00-A04": 708, "MA05-A14": 2792, "MA15-A34": 4392, "MA35-A59": 6870, "MA60-A79": 2541, "MA80+": 708}, "J": {"WA00-A04": 936, "WA05-A14": 2679, "WA15-A34": 6225, "WA35-A59": 6345, "WA60-A79": 1532, "WA80+": 798, "MA00-A04": 1020, "MA05-A14": 2780, "MA15-A34": 5583, "MA35-A59": 5673, "MA60-A79": 1416, "MA80+": 469}, "KYF": {"WA00-A04": 261, "WA05-A14": 1342, "WA15-A34": 2774, "WA35-A59": 4913, "WA60-A79": 1817, "WA80+": 729, "MA00-A04": 276, "MA05-A14": 1489, "MA15-A34": 2492, "MA35-A59": 4043, "MA60-A79": 1595, "MA80+": 390}, "NDH": {"WA00-A04": 438, "WA05-A14": 1757, "WA15-A34": 3187, "WA35-A59": 5072, "WA60-A79": 1579, "WA80+": 676, "MA00-A04": 429, "MA05-A14": 1835, "MA15-A34": 2801, "MA35-A59": 4274, "MA60-A79": 1487, "MA80+": 379}, "SHK": {"WA00-A04": 527, "WA05-A14": 2142, "WA15-A34": 3484, "WA35-A59": 6544, "WA60-A79": 2217, "WA80+": 799, "MA00-A04": 511, "MA05-A14": 2197, "MA15-A34": 3216, "MA35-A59": 5675, "MA60-A79": 1957, "MA80+": 482}, "SOK": {"WA00-A04": 322, "WA05-A14": 1600, "WA15-A34": 3572, "WA35-A59": 6732, "WA60-A79": 2416, "WA80+": 871, "MA00-A04": 361, "MA05-A14": 1723, "MA15-A34": 3372, "MA35-A59": 5707, "MA60-A79": 2248, "MA80+": 509}, "SLF": {"WA00-A04": 419, "WA05-A14": 2087, "WA15-A34": 4180, "WA35-A59": 7941, "WA60-A79": 2883, "WA80+": 1388, "MA00-A04": 451, "MA05-A14": 2178, "MA15-A34": 3742, "MA35-A59": 6850, "MA60-A79": 2586, "MA80+": 682}, "SM": {"WA00-A04": 573, "WA05-A14": 2665, "WA15-A34": 5349, "WA35-A59": 9639, "WA60-A79": 3525, "WA80+": 1479, "MA00-A04": 571, "MA05-A14": 2816, "MA15-A34": 4932, "MA35-A59": 8194, "MA60-A79": 3413, "MA80+": 855}, "SOM": {"WA00-A04": 329, "WA05-A14": 1526, "WA15-A34": 2822, "WA35-A59": 5156, "WA60-A79": 1757, "WA80+": 665, "MA00-A04": 332, "MA05-A14": 1629, "MA15-A34": 2476, "MA35-A59": 4448, "MA60-A79": 1552, "MA80+": 364}, "SON": {"WA00-A04": 213, "WA05-A14": 1132, "WA15-A34": 2411, "WA35-A59": 4356, "WA60-A79": 1685, "WA80+": 741, "MA00-A04": 212, "MA05-A14": 1176, "MA15-A34": 2259, "MA35-A59": 3959, "MA60-A79": 1555, "MA80+": 405}, "SHL": {"WA00-A04": 95, "WA05-A14": 563, "WA15-A34": 1295, "WA35-A59": 2151, "WA60-A79": 935, "WA80+": 410, "MA00-A04": 109, "MA05-A14": 589, "MA15-A34": 1291, "MA35-A59": 1872, "MA60-A79": 859, "MA80+": 213}, "UH": {"WA00-A04": 535, "WA05-A14": 2252, "WA15-A34": 4334, "WA35-A59": 7551, "WA60-A79": 2582, "WA80+": 1126, "MA00-A04": 489, "MA05-A14": 2278, "MA15-A34": 3821, "MA35-A59": 6250, "MA60-A79": 2365, "MA80+": 641}, "WAK": {"WA00-A04": 732, "WA05-A14": 3389, "WA15-A34": 6335, "WA35-A59": 11152, "WA60-A79": 3541, "WA80+": 1608, "MA00-A04": 793, "MA05-A14": 3634, "MA15-A34": 5788, "MA35-A59": 9665, "MA60-A79": 3441, "MA80+": 900}, "WE": {"WA00-A04": 476, "WA05-A14": 1853, "WA15-A34": 3326, "WA35-A59": 4266, "WA60-A79": 1210, "WA80+": 674, "MA00-A04": 515, "MA05-A14": 1772, "MA15-A34": 2822, "MA35-A59": 3472, "MA60-A79": 1082, "MA80+": 361}, "AP": {"WA00-A04": 512, "WA05-A14": 2198, "WA15-A34": 3332, "WA35-A59": 5854, "WA60-A79": 1722, "WA80+": 637, "MA00-A04": 533, "MA05-A14": 2154, "MA15-A34": 2840, "MA35-A59": 5046, "MA60-A79": 1595, "MA80+": 345}}}