{"ts": false, "types": {"WA00-A04": {"id": 0, "de": "W: A00-A04", "color": "#0000d3", "unit": "F\u00e4lle", "unit1": "Fall", "showSum": 1}, "WA05-A14": {"id": 1, "de": "W: A05-A14", "color": "#0000d3", "unit": "F\u00e4lle", "unit1": "Fall", "showSum": 1}, "WA15-A34": {"id": 2, "de": "W: A15-A34", "color": "#0000d3", "unit": "F\u00e4lle", "unit1": "Fall", "showSum": 1}, "WA35-A59": {"id": 3, "de": "W: A35-A59", "color": "#0000d3", "unit": "F\u00e4lle", "unit1": "Fall", "showSum": 1}, "WA60-A79": {"id": 4, "de": "W: A60-A79", "color": "#0000d3", "unit": "F\u00e4lle", "unit1": "Fall", "showSum": 1}, "WA80+": {"id": 5, "de": "W: A80+", "color": "#0000d3", "unit": "F\u00e4lle", "unit1": "Fall", "showSum": 1}, "MA00-A04": {"id": 6, "de": "M: A00-A04", "color": "#0000d3", "unit": "F\u00e4lle", "unit1": "Fall", "showSum": 1}, "MA05-A14": {"id": 7, "de": "M: A05-A14", "color": "#0000d3", "unit": "F\u00e4lle", "unit1": "Fall", "showSum": 1}, "MA15-A34": {"id": 8, "de": "M: A15-A34", "color": "#0000d3", "unit": "F\u00e4lle", "unit1": "Fall", "showSum": 1}, "MA35-A59": {"id": 9, "de": "M: A35-A59", "color": "#0000d3", "unit": "F\u00e4lle", "unit1": "Fall", "showSum": 1}, "MA60-A79": {"id": 10, "de": "M: A60-A79", "color": "#0000d3", "unit": "F\u00e4lle", "unit1": "Fall", "showSum": 1}, "MA80+": {"id": 11, "de": "M: A80+", "color": "#0000d3", "unit": "F\u00e4lle", "unit1": "Fall", "showSum": 1}}, "values": {"ABG": {"WA00-A04": 89, "WA05-A14": 342, "WA15-A34": 641, "WA35-A59": 1013, "WA60-A79": 294, "WA80+": 87, "MA00-A04": 99, "MA05-A14": 292, "MA15-A34": 576, "MA35-A59": 894, "MA60-A79": 249, "MA80+": 57}, "EIC": {"WA00-A04": 166, "WA05-A14": 514, "WA15-A34": 814, "WA35-A59": 1179, "WA60-A79": 305, "WA80+": 67, "MA00-A04": 173, "MA05-A14": 567, "MA15-A34": 638, "MA35-A59": 1064, "MA60-A79": 271, "MA80+": 48}, "EA": {"WA00-A04": 0, "WA05-A14": 0, "WA15-A34": 0, "WA35-A59": 0, "WA60-A79": 0, "WA80+": 0, "MA00-A04": 0, "MA05-A14": 0, "MA15-A34": 0, "MA35-A59": 0, "MA60-A79": 0, "MA80+": 0}, "EF": {"WA00-A04": 20, "WA05-A14": 95, "WA15-A34": 145, "WA35-A59": 174, "WA60-A79": 42, "WA80+": 87, "MA00-A04": 24, "MA05-A14": 84, "MA15-A34": 121, "MA35-A59": 147, "MA60-A79": 49, "MA80+": 43}, "G": {"WA00-A04": 37, "WA05-A14": 144, "WA15-A34": 396, "WA35-A59": 527, "WA60-A79": 143, "WA80+": 70, "MA00-A04": 36, "MA05-A14": 190, "MA15-A34": 354, "MA35-A59": 457, "MA60-A79": 139, "MA80+": 34}, "GTH": {"WA00-A04": 50, "WA05-A14": 173, "WA15-A34": 383, "WA35-A59": 565, "WA60-A79": 140, "WA80+": 38, "MA00-A04": 62, "MA05-A14": 176, "MA15-A34": 340, "MA35-A59": 465, "MA60-A79": 125, "MA80+": 19}, "GRZ": {"WA00-A04": 32, "WA05-A14": 168, "WA15-A34": 364, "WA35-A59": 578, "WA60-A79": 120, "WA80+": 55, "MA00-A04": 23, "MA05-A14": 178, "MA15-A34": 298, "MA35-A59": 445, "MA60-A79": 116, "MA80+": 28}, "HBN": {"WA00-A04": 32, "WA05-A14": 157, "WA15-A34": 349, "WA35-A59": 548, "WA60-A79": 145, "WA80+": 46, "MA00-A04": 41, "MA05-A14": 161, "MA15-A34": 316, "MA35-A59": 535, "MA60-A79": 146, "MA80+": 21}, "IK": {"WA00-A04": 58, "WA05-A14": 189, "WA15-A34": 302, "WA35-A59": 452, "WA60-A79": 128, "WA80+": 36, "MA00-A04": 55, "MA05-A14": 172, "MA15-A34": 270, "MA35-A59": 412, "MA60-A79": 117, "MA80+": 29}, "J": {"WA00-A04": 182, "WA05-A14": 463, "WA15-A34": 980, "WA35-A59": 945, "WA60-A79": 183, "WA80+": 62, "MA00-A04": 187, "MA05-A14": 475, "MA15-A34": 867, "MA35-A59": 862, "MA60-A79": 158, "MA80+": 37}, "KYF": {"WA00-A04": 20, "WA05-A14": 92, "WA15-A34": 187, "WA35-A59": 334, "WA60-A79": 109, "WA80+": 34, "MA00-A04": 26, "MA05-A14": 119, "MA15-A34": 143, "MA35-A59": 278, "MA60-A79": 103, "MA80+": 15}, "NDH": {"WA00-A04": 93, "WA05-A14": 298, "WA15-A34": 536, "WA35-A59": 768, "WA60-A79": 195, "WA80+": 105, "MA00-A04": 87, "MA05-A14": 332, "MA15-A34": 428, "MA35-A59": 639, "MA60-A79": 211, "MA80+": 45}, "SHK": {"WA00-A04": 127, "WA05-A14": 441, "WA15-A34": 731, "WA35-A59": 1166, "WA60-A79": 291, "WA80+": 115, "MA00-A04": 141, "MA05-A14": 468, "MA15-A34": 661, "MA35-A59": 1023, "MA60-A79": 254, "MA80+": 56}, "SOK": {"WA00-A04": 59, "WA05-A14": 254, "WA15-A34": 533, "WA35-A59": 767, "WA60-A79": 223, "WA80+": 44, "MA00-A04": 76, "MA05-A14": 252, "MA15-A34": 485, "MA35-A59": 703, "MA60-A79": 196, "MA80+": 25}, "SLF": {"WA00-A04": 40, "WA05-A14": 243, "WA15-A34": 477, "WA35-A59": 773, "WA60-A79": 218, "WA80+": 95, "MA00-A04": 52, "MA05-A14": 291, "MA15-A34": 444, "MA35-A59": 745, "MA60-A79": 205, "MA80+": 38}, "SM": {"WA00-A04": 61, "WA05-A14": 210, "WA15-A34": 408, "WA35-A59": 620, "WA60-A79": 179, "WA80+": 59, "MA00-A04": 62, "MA05-A14": 242, "MA15-A34": 369, "MA35-A59": 569, "MA60-A79": 152, "MA80+": 30}, "SOM": {"WA00-A04": 24, "WA05-A14": 135, "WA15-A34": 206, "WA35-A59": 348, "WA60-A79": 88, "WA80+": 30, "MA00-A04": 20, "MA05-A14": 138, "MA15-A34": 162, "MA35-A59": 282, "MA60-A79": 80, "MA80+": 24}, "SON": {"WA00-A04": 21, "WA05-A14": 124, "WA15-A34": 310, "WA35-A59": 457, "WA60-A79": 97, "WA80+": 48, "MA00-A04": 29, "MA05-A14": 139, "MA15-A34": 271, "MA35-A59": 440, "MA60-A79": 99, "MA80+": 21}, "SHL": {"WA00-A04": 7, "WA05-A14": 42, "WA15-A34": 109, "WA35-A59": 161, "WA60-A79": 54, "WA80+": 20, "MA00-A04": 8, "MA05-A14": 54, "MA15-A34": 105, "MA35-A59": 143, "MA60-A79": 56, "MA80+": 10}, "UH": {"WA00-A04": 60, "WA05-A14": 186, "WA15-A34": 354, "WA35-A59": 569, "WA60-A79": 164, "WA80+": 72, "MA00-A04": 45, "MA05-A14": 185, "MA15-A34": 304, "MA35-A59": 459, "MA60-A79": 127, "MA80+": 23}, "WAK": {"WA00-A04": 78, "WA05-A14": 359, "WA15-A34": 702, "WA35-A59": 1057, "WA60-A79": 245, "WA80+": 75, "MA00-A04": 84, "MA05-A14": 407, "MA15-A34": 663, "MA35-A59": 904, "MA60-A79": 263, "MA80+": 53}, "WE": {"WA00-A04": 58, "WA05-A14": 277, "WA15-A34": 550, "WA35-A59": 570, "WA60-A79": 137, "WA80+": 33, "MA00-A04": 50, "MA05-A14": 235, "MA15-A34": 471, "MA35-A59": 481, "MA60-A79": 128, "MA80+": 31}, "AP": {"WA00-A04": 59, "WA05-A14": 285, "WA15-A34": 436, "WA35-A59": 761, "WA60-A79": 170, "WA80+": 85, "MA00-A04": 69, "MA05-A14": 258, "MA15-A34": 415, "MA35-A59": 636, "MA60-A79": 164, "MA80+": 44}}}